num2bangla/__init__.py
num2bangla/cli.py
num2bangla/converter.py
num2bangla-1.0.0.dist-info/LICENSE
num2bangla-1.0.0.dist-info/METADATA
num2bangla-1.0.0.dist-info/WHEEL
num2bangla-1.0.0.dist-info/entry_points.txt
num2bangla-1.0.0.dist-info/top_level.txt
num2bangla-1.0.0.dist-info/RECORD
