Metadata-Version: 2.1
Name: num2bangla
Version: 1.0.0
Summary: A package to convert numbers to Bengali/Bangla text and numerals with currency formatting support
Home-page: https://github.com/Mamuntheprogrammer/num2bangla
Author: Md.Amanullah Al Mamun
Author-email: pygemsbd@gmail.com
License: MIT
Project-URL: Source, https://github.com/Mamuntheprogrammer/num2bangla
Project-URL: Bug Tracker, https://github.com/Mamuntheprogrammer/num2bangla/issues
Keywords: bangla,bengali,numbers,num2words,currency,text,numerals
Classifier: Programming Language :: Python :: 3
Classifier: License :: OSI Approved :: MIT License
Classifier: Operating System :: OS Independent
Requires-Python: >=3.6
License-File: LICENSE
